param_lsp/__init__.py
param_lsp/__main__.py
param_lsp/__version.py
param_lsp/_check.py
param_lsp/_logging.py
param_lsp/_types.py
param_lsp/_version.py
param_lsp/analyzer.py
param_lsp/cache.py
param_lsp/constants.py
param_lsp/models.py
param_lsp/py.typed
param_lsp/server.py
param_lsp/_analyzer/__init__.py
param_lsp/_analyzer/ast_navigator.py
param_lsp/_analyzer/import_resolver.py
param_lsp/_analyzer/inheritance_resolver.py
param_lsp/_analyzer/parameter_extractor.py
param_lsp/_analyzer/python_environment.py
param_lsp/_analyzer/static_external_analyzer.py
param_lsp/_analyzer/validation.py
param_lsp/_server/__init__.py
param_lsp/_server/base.py
param_lsp/_server/completion.py
param_lsp/_server/hover.py
param_lsp/_server/validation.py
param_lsp/_treesitter/__init__.py
param_lsp/_treesitter/parser.py
param_lsp/_treesitter/queries.py
param_lsp/_treesitter/utils.py
param_lsp-0.0.1b23.data/data/etc/jupyter/jupyter_server_config.d/param-lsp-jupyter.json
param_lsp-0.0.1b23.dist-info/METADATA
param_lsp-0.0.1b23.dist-info/WHEEL
param_lsp-0.0.1b23.dist-info/entry_points.txt
param_lsp-0.0.1b23.dist-info/licenses/LICENSE.txt
param_lsp-0.0.1b23.dist-info/RECORD
